{"v":"5.9.0","fr":30,"ip":0,"op":150,"w":500,"h":500,"nm":"Partly Cloudy","ddd":0,"assets":[],"layers":[{"ty":4,"nm":"Sun","ind":1,"ip":0,"op":150,"sr":1,"st":0,"bm":0,"hd":false,"ao":0,"ddd":0,"ks":{"a":{"a":0,"k":[0,0,0]},"p":{"a":0,"k":[330,155,0]},"s":{"a":1,"k":[{"t":0,"s":[95,95,100],"i":{"x":[0.5],"y":[0.5]},"o":{"x":[0.5],"y":[0.5]}},{"t":75,"s":[108,108,100],"i":{"x":[0.5],"y":[0.5]},"o":{"x":[0.5],"y":[0.5]}},{"t":150,"s":[95,95,100],"i":{"x":[0.5],"y":[0.5]},"o":{"x":[0.5],"y":[0.5]}}]},"r":{"a":1,"k":[{"t":0,"s":[0],"i":{"x":[0.5],"y":[0.5]},"o":{"x":[0.5],"y":[0.5]}},{"t":150,"s":[25],"i":{"x":[0.5],"y":[0.5]},"o":{"x":[0.5],"y":[0.5]}}]},"o":{"a":0,"k":100}},"shapes":[{"ty":"gr","nm":"SC","hd":false,"it":[{"ty":"el","nm":"El","d":1,"hd":false,"p":{"a":0,"k":[0,0]},"s":{"a":0,"k":[100,100]}},{"ty":"fl","nm":"Fill","hd":false,"r":1,"c":{"a":0,"k":[1,0.8235294117647058,0.1568627450980392,1]},"o":{"a":0,"k":100}},{"ty":"tr","nm":"T","hd":false,"a":{"a":0,"k":[0,0]},"p":{"a":0,"k":[0,0]},"s":{"a":0,"k":[100,100]},"r":{"a":0,"k":0},"o":{"a":0,"k":100},"sk":{"a":0,"k":0},"sa":{"a":0,"k":0}}]},{"ty":"gr","nm":"SG","hd":false,"it":[{"ty":"el","nm":"El","d":1,"hd":false,"p":{"a":0,"k":[0,0]},"s":{"a":0,"k":[140,140]}},{"ty":"fl","nm":"Fill","hd":false,"r":1,"c":{"a":0,"k":[1,0.7843137254901961,0.11764705882352941,1]},"o":{"a":0,"k":100}},{"ty":"tr","nm":"T","hd":false,"a":{"a":0,"k":[0,0]},"p":{"a":0,"k":[0,0]},"s":{"a":0,"k":[100,100]},"r":{"a":0,"k":0},"o":{"a":0,"k":25},"sk":{"a":0,"k":0},"sa":{"a":0,"k":0}}]}]},{"ty":4,"nm":"Cloud","ind":2,"ip":0,"op":150,"sr":1,"st":0,"bm":0,"hd":false,"ao":0,"ddd":0,"ks":{"a":{"a":0,"k":[0,0,0]},"p":{"a":1,"k":[{"t":0,"s":[240,265,0],"i":{"x":[0.5],"y":[0.5]},"o":{"x":[0.5],"y":[0.5]}},{"t":75,"s":[240,258,0],"i":{"x":[0.5],"y":[0.5]},"o":{"x":[0.5],"y":[0.5]}},{"t":150,"s":[240,265,0],"i":{"x":[0.5],"y":[0.5]},"o":{"x":[0.5],"y":[0.5]}}]},"s":{"a":0,"k":[100,100,100]},"r":{"a":0,"k":0},"o":{"a":0,"k":100}},"shapes":[{"ty":"gr","nm":"CL","hd":false,"it":[{"ty":"el","nm":"El","d":1,"hd":false,"p":{"a":0,"k":[0,0]},"s":{"a":0,"k":[200,110]}},{"ty":"el","nm":"El","d":1,"hd":false,"p":{"a":0,"k":[80,-20]},"s":{"a":0,"k":[160,95]}},{"ty":"el","nm":"El","d":1,"hd":false,"p":{"a":0,"k":[-80,-15]},"s":{"a":0,"k":[140,88]}},{"ty":"fl","nm":"Fill","hd":false,"r":1,"c":{"a":0,"k":[0.8823529411764706,0.9215686274509803,0.9882352941176471,1]},"o":{"a":0,"k":100}},{"ty":"tr","nm":"T","hd":false,"a":{"a":0,"k":[0,0]},"p":{"a":0,"k":[0,0]},"s":{"a":0,"k":[100,100]},"r":{"a":0,"k":0},"o":{"a":0,"k":100},"sk":{"a":0,"k":0},"sa":{"a":0,"k":0}}]}]},{"ty":4,"nm":"Shadow","ind":3,"ip":0,"op":150,"sr":1,"st":0,"bm":0,"hd":false,"ao":0,"ddd":0,"ks":{"a":{"a":0,"k":[0,0,0]},"p":{"a":1,"k":[{"t":0,"s":[240,275,0],"i":{"x":[0.5],"y":[0.5]},"o":{"x":[0.5],"y":[0.5]}},{"t":75,"s":[240,268,0],"i":{"x":[0.5],"y":[0.5]},"o":{"x":[0.5],"y":[0.5]}},{"t":150,"s":[240,275,0],"i":{"x":[0.5],"y":[0.5]},"o":{"x":[0.5],"y":[0.5]}}]},"s":{"a":0,"k":[100,100,100]},"r":{"a":0,"k":0},"o":{"a":0,"k":18}},"shapes":[{"ty":"gr","nm":"SH","hd":false,"it":[{"ty":"el","nm":"El","d":1,"hd":false,"p":{"a":0,"k":[0,0]},"s":{"a":0,"k":[195,30]}},{"ty":"fl","nm":"Fill","hd":false,"r":1,"c":{"a":0,"k":[0.39215686274509803,0.47058823529411764,0.6274509803921569,1]},"o":{"a":0,"k":100}},{"ty":"tr","nm":"T","hd":false,"a":{"a":0,"k":[0,0]},"p":{"a":0,"k":[0,0]},"s":{"a":0,"k":[100,100]},"r":{"a":0,"k":0},"o":{"a":0,"k":100},"sk":{"a":0,"k":0},"sa":{"a":0,"k":0}}]}]}]}